mrd/__init__.py
mrd/_binary.py
mrd/_dtypes.py
mrd/_ndjson.py
mrd/binary.py
mrd/ndjson.py
mrd/protocols.py
mrd/types.py
mrd/yardl_types.py
mrd/tools/export_png_images.py
mrd/tools/ismrmrd_to_mrd.py
mrd/tools/minimal_example.py
mrd/tools/mrd_to_ismrmrd.py
mrd/tools/phantom.py
mrd/tools/simulation.py
mrd/tools/stream_recon.py
mrd/tools/transform.py
mrd_python-2.2.0.dist-info/METADATA
mrd_python-2.2.0.dist-info/WHEEL
mrd_python-2.2.0.dist-info/top_level.txt
mrd_python-2.2.0.dist-info/RECORD
