Metadata-Version: 2.4
Name: mrd-python
Version: 2.2.0
Summary: Library and tools for working with data in the ISMRM Raw Data (MRD) format.
Project-URL: Homepage, https://ismrmrd.github.io/mrd
Project-URL: Documentation, https://ismrmrd.github.io/mrd
Project-URL: Repository, https://github.com/ismrmrd/mrd
Classifier: Development Status :: 5 - Production/Stable
Classifier: Programming Language :: Python :: 3
Classifier: License :: OSI Approved :: MIT License
Classifier: Operating System :: OS Independent
Classifier: Intended Audience :: Science/Research
Classifier: Topic :: Scientific/Engineering :: Medical Science Apps.
Requires-Python: >=3.12
Requires-Dist: ismrmrd>=1.14.2
Requires-Dist: numpy>=1.22.0
Requires-Dist: pillow>=9.2.0
